lptrack/__init__.py
lptrack/codec.py
lptrack/format.py
lptrack/sources.py
lptrack/strcodec.py
lptrack/track.py
lptrack/versions.py
lptrack-1.0.0.dist-info/LICENSE
lptrack-1.0.0.dist-info/METADATA
lptrack-1.0.0.dist-info/WHEEL
lptrack-1.0.0.dist-info/top_level.txt
lptrack-1.0.0.dist-info/RECORD
