Metadata-Version: 2.1
Name: lptrack
Version: 1.0.0
Summary: UNKNOWN
Home-page: https://github.com/gieseladev/lptrack
Author: Giesela Inc.
Author-email: team@giesela.dev
License: MIT
Platform: UNKNOWN
Requires-Python: ~=3.7
Requires-Dist: ftfy
